mlia/__init__.py
mlia/api.py
mlia/backend/__init__.py
mlia/backend/config.py
mlia/backend/errors.py
mlia/backend/install.py
mlia/backend/manager.py
mlia/backend/registry.py
mlia/backend/repo.py
mlia/backend/armnn_tflite_delegate/__init__.py
mlia/backend/armnn_tflite_delegate/compat.py
mlia/backend/armnn_tflite_delegate/ops/__init__.py
mlia/backend/armnn_tflite_delegate/ops/v22_08.py
mlia/backend/armnn_tflite_delegate/ops/v22_11.py
mlia/backend/armnn_tflite_delegate/ops/v23_05.py
mlia/backend/corstone/__init__.py
mlia/backend/corstone/install.py
mlia/backend/corstone/performance.py
mlia/backend/tosa_checker/__init__.py
mlia/backend/tosa_checker/compat.py
mlia/backend/tosa_checker/install.py
mlia/backend/vela/__init__.py
mlia/backend/vela/compat.py
mlia/backend/vela/compiler.py
mlia/backend/vela/install.py
mlia/backend/vela/performance.py
mlia/cli/__init__.py
mlia/cli/command_validators.py
mlia/cli/commands.py
mlia/cli/common.py
mlia/cli/helpers.py
mlia/cli/main.py
mlia/cli/options.py
mlia/core/__init__.py
mlia/core/advice_generation.py
mlia/core/advisor.py
mlia/core/common.py
mlia/core/context.py
mlia/core/data_analysis.py
mlia/core/data_collection.py
mlia/core/errors.py
mlia/core/events.py
mlia/core/handlers.py
mlia/core/helpers.py
mlia/core/logging.py
mlia/core/metadata.py
mlia/core/mixins.py
mlia/core/performance.py
mlia/core/reporters.py
mlia/core/reporting.py
mlia/core/typing.py
mlia/core/workflow.py
mlia/nn/__init__.py
mlia/nn/common.py
mlia/nn/select.py
mlia/nn/rewrite/__init__.py
mlia/nn/rewrite/core/__init__.py
mlia/nn/rewrite/core/extract.py
mlia/nn/rewrite/core/rewrite.py
mlia/nn/rewrite/core/train.py
mlia/nn/rewrite/core/graph_edit/__init__.py
mlia/nn/rewrite/core/graph_edit/cut.py
mlia/nn/rewrite/core/graph_edit/diff.py
mlia/nn/rewrite/core/graph_edit/join.py
mlia/nn/rewrite/core/graph_edit/record.py
mlia/nn/rewrite/core/utils/__init__.py
mlia/nn/rewrite/core/utils/numpy_tfrecord.py
mlia/nn/rewrite/core/utils/parallel.py
mlia-0.9.2.dist-info/licenses/LICENSES/Apache-2.0.txt
mlia-0.9.2.dist-info/licenses/LICENSES/BSD-2-Clause.txt
mlia-0.9.2.dist-info/licenses/LICENSES/BSD-3-Clause.txt
mlia-0.9.2.dist-info/licenses/LICENSES/CC-PDDC.txt
mlia-0.9.2.dist-info/licenses/LICENSES/MIT.txt
mlia-0.9.2.dist-info/METADATA
mlia-0.9.2.dist-info/WHEEL
mlia-0.9.2.dist-info/entry_points.txt
mlia-0.9.2.dist-info/top_level.txt
mlia-0.9.2.dist-info/RECORD
