Metadata-Version: 2.4
Name: mlia
Version: 0.9.2
Summary: ML Inference Advisor
Home-page: https://github.com/arm/mlia.git
Author: Arm Ltd
Author-email: mlia@arm.com
License: Apache-2.0
Keywords: ml,arm,ethos-u,tflite
Classifier: Development Status :: 4 - Beta
Classifier: Intended Audience :: Developers
Classifier: Operating System :: POSIX :: Linux
Classifier: Programming Language :: Python :: 3
Classifier: Programming Language :: Python :: 3.8
Classifier: Topic :: Scientific/Engineering :: Artificial Intelligence
Requires-Python: >=3.9.0
License-File: LICENSES/Apache-2.0.txt
License-File: LICENSES/BSD-2-Clause.txt
License-File: LICENSES/BSD-3-Clause.txt
License-File: LICENSES/CC-PDDC.txt
License-File: LICENSES/MIT.txt
Requires-Dist: tensorflow==2.15.1
Requires-Dist: h5py==3.10.0
Requires-Dist: tensorflow-model-optimization~=0.7.5
Requires-Dist: requests~=2.32.3
Requires-Dist: rich~=13.7.1
Requires-Dist: tomli>=2.0.1; python_version < "3.11"
Dynamic: description
Dynamic: license-file
